{
    "jquery": {
        "source": "http://code.jquery.com/jquery-VERSION.min.js",
        "version": "2.1.4",
        "target": "static/jquery.min.js"
    },
    
    "underscore": {
        "source": "https://raw.github.com/jashkenas/underscore/VERSION/underscore-min.js",
        "version": "1.8.3",
        "target": "static/underscore-min.js"
    },
    
    "yui-reset": {
        "source": "http://yui.yahooapis.com/VERSION/build/cssreset/cssreset-min.css",
        "version": "3.18.1",
        "target": "static/cssreset-min.css"
    },

    "jquery-tiny-pubsub": {
        "source": "https://raw.github.com/cowboy/jquery-tiny-pubsub/VERSION/src/tiny-pubsub.js",
        "version": "0.7.0",
        "target": "static/tiny-pubsub.js"
    },
        
    "js_lib_websocket": {
        "source": "https://raw.githubusercontent.com/calaldees/libs/master/js/websocket.js",
        "version": "0.0.0",
        "target": "static/websocket.js"
    },
    
    "js_lib_music": {
        "source": "https://raw.githubusercontent.com/calaldees/libs/master/js/music.js",
        "version": "0.0.0",
        "target": "static/music.js"
    },

    "js_lib_utils": {
        "source": "https://raw.githubusercontent.com/calaldees/libs/master/js/utils.js",
        "version": "0.0.0",
        "target": "static/utils.js"
    }
   
}
